{
  "replace":[["[0-9]+\\.[0-9]+","NUM"],
             ["[0-9]+","NUM"],
             ["\\xa0"," "],
             ["[_\\\"\\`@#%&\\*\\+=\\|\\^\\[\\]\\{\\}\\(\\)\\<\\>\\/\\\\]+"," "],
             ["([a-z])\\1{2,}","\\1\\1"],
             ["([^-\\s,:;.?!])([-,:;.?!])","\\1 \\2"],
             ["([-,:;.?!])([^-\\s,:;.?!])","\\1 \\2"],
             ["([,:;])\\1*"," \\1 "],
             ["([!?])\\1+"," \\1\\1 "],
             ["([.])\\1+"," \\1\\1\\1 "],
             ["'*\\s+'*"," "],
             ["^","START "],
             ["$"," END"]
            ],
  "tokenizer":{"name":"RegexpTokenizer","kwargs":{"pattern":"\\s+","gaps":true,"discard_empty":true}},
  "sequence":["lower","replace","tokenize"],
  "ngrams":{"n":[1,2]}
}
